timewarrior_balance/__init__.py
timewarrior_balance/__main__.py
timewarrior_balance/balance.py
timewarrior_balance-0.2.1.dist-info/LICENSE.txt
timewarrior_balance-0.2.1.dist-info/METADATA
timewarrior_balance-0.2.1.dist-info/WHEEL
timewarrior_balance-0.2.1.dist-info/top_level.txt
timewarrior_balance-0.2.1.dist-info/RECORD
