Metadata-Version: 2.1
Name: timewarrior-balance
Version: 0.2.1
Summary: Get a balance of your timewarrior hours
Home-page: https://github.com/guludo/timewarrior-balance
Keywords: timewarrior
Classifier: Development Status :: 4 - Beta
Classifier: Environment :: Console
Classifier: Intended Audience :: End Users/Desktop
Classifier: License :: OSI Approved :: Mozilla Public License 2.0 (MPL 2.0)
Classifier: Programming Language :: Python :: 3
Classifier: Topic :: Utilities
License-File: LICENSE.txt
